attercop/__init__.py
attercop/attercop.py
attercop-0.3.4.dist-info/LICENSE
attercop-0.3.4.dist-info/METADATA
attercop-0.3.4.dist-info/WHEEL
attercop-0.3.4.dist-info/entry_points.txt
attercop-0.3.4.dist-info/top_level.txt
attercop-0.3.4.dist-info/RECORD
