Metadata-Version: 2.1
Name: attercop
Version: 0.3.4
Author-email: Mark Snidal <mark.snidal@gmail.com>
License: GPL-3.0-or-later
Requires-Python: >=3.7.1
License-File: LICENSE
Requires-Dist: openai (~=0.26.1)
Requires-Dist: pyperclip (~=1.8.2)
Requires-Dist: colorama (~=0.4.6)
Provides-Extra: lint
Requires-Dist: black (~=22.12.0) ; extra == 'lint'
Provides-Extra: test
Requires-Dist: pytest (~=7.2.1) ; extra == 'test'
Requires-Dist: pytest-mock (~=3.10.0) ; extra == 'test'
